{"title":"Zigbee课程设计前后端说明文档","uid":"de7d76ad0250eaff2996ee8d23dbe313","slug":"说明文档","date":"2022-12-21T13:44:42.840Z","updated":"2022-12-21T14:04:50.379Z","comments":true,"path":"api/articles/说明文档.json","keywords":null,"cover":[],"content":"<h2 id=\"环境说明：\"><a href=\"#环境说明：\" class=\"headerlink\" title=\"环境说明：\"></a>环境说明：</h2><blockquote><span class=\"custom-blockquote-svg\"><svg width=\"24\" height=\"24\" viewBox=\"0 0 24 24\" fill=\"\" xmlns=\"http://www.w3.org/2000/svg\" data-reactroot=\"\">\n<path fill=\"\" d=\"M22 12C22 6.5 17.5 2 12 2C6.5 2 2 6.5 2 12C2 17.5 6.5 22 12 22C13.8 22 15.5 21.5 17 20.6L22 22L20.7 17C21.5 15.5 22 13.8 22 12Z\" undefined=\"1\"></path>\n<path fill=\"\" d=\"M15.97 11.5H16.04C17.12 11.5 18 12.38 18 13.47V13.53C18 14.62 17.12 15.5 16.03 15.5H15.96C14.88 15.5 14 14.62 14 13.53V13.46C14 12.38 14.88 11.5 15.97 11.5Z\" undefined=\"1\"></path>\n<path fill=\"\" d=\"M7.97 11.5H8.04C9.12 11.5 10 12.38 10 13.47V13.53C10 14.62 9.12 15.5 8.03 15.5H7.97C6.88 15.5 6 14.62 6 13.53V13.46C6 12.38 6.88 11.5 7.97 11.5Z\" undefined=\"1\"></path>\n<path stroke-linejoin=\"round\" stroke-linecap=\"round\" stroke-miterlimit=\"10\" stroke-width=\"2\" stroke=\"\" d=\"M17 8.5C15.23 8.97 14.07 10.84 14.01 13.27C14 13.33 14 13.4 14 13.47V13.5\"></path>\n<path stroke-linejoin=\"round\" stroke-linecap=\"round\" stroke-miterlimit=\"10\" stroke-width=\"2\" stroke=\"\" d=\"M9 8.5C7.23 8.97 6.07 10.84 6.01 13.27C6 13.33 6 13.4 6 13.47V13.5\"></path>\n<path stroke-linejoin=\"round\" stroke-linecap=\"round\" stroke-miterlimit=\"10\" stroke-width=\"2\" stroke=\"\" d=\"M15.97 11.5H16.04C17.12 11.5 18 12.38 18 13.47V13.53C18 14.62 17.12 15.5 16.03 15.5H15.96C14.88 15.5 14 14.62 14 13.53V13.46C14 12.38 14.88 11.5 15.97 11.5Z\"></path>\n<path stroke-linejoin=\"round\" stroke-linecap=\"round\" stroke-miterlimit=\"10\" stroke-width=\"2\" stroke=\"\" d=\"M7.97 11.5H8.04C9.12 11.5 10 12.38 10 13.47V13.53C10 14.62 9.12 15.5 8.03 15.5H7.97C6.88 15.5 6 14.62 6 13.53V13.46C6 12.38 6.88 11.5 7.97 11.5Z\"></path>\n</svg>\n</span><p>开发软件环境：IDEA 2022.2.3+Postman+MicroSoft Sqlserver Manager 2015</p></blockquote>\n<blockquote><span class=\"custom-blockquote-svg\"><svg width=\"24\" height=\"24\" viewBox=\"0 0 24 24\" fill=\"\" xmlns=\"http://www.w3.org/2000/svg\" data-reactroot=\"\">\n<path fill=\"\" d=\"M22 12C22 6.5 17.5 2 12 2C6.5 2 2 6.5 2 12C2 17.5 6.5 22 12 22C13.8 22 15.5 21.5 17 20.6L22 22L20.7 17C21.5 15.5 22 13.8 22 12Z\" undefined=\"1\"></path>\n<path fill=\"\" d=\"M15.97 11.5H16.04C17.12 11.5 18 12.38 18 13.47V13.53C18 14.62 17.12 15.5 16.03 15.5H15.96C14.88 15.5 14 14.62 14 13.53V13.46C14 12.38 14.88 11.5 15.97 11.5Z\" undefined=\"1\"></path>\n<path fill=\"\" d=\"M7.97 11.5H8.04C9.12 11.5 10 12.38 10 13.47V13.53C10 14.62 9.12 15.5 8.03 15.5H7.97C6.88 15.5 6 14.62 6 13.53V13.46C6 12.38 6.88 11.5 7.97 11.5Z\" undefined=\"1\"></path>\n<path stroke-linejoin=\"round\" stroke-linecap=\"round\" stroke-miterlimit=\"10\" stroke-width=\"2\" stroke=\"\" d=\"M17 8.5C15.23 8.97 14.07 10.84 14.01 13.27C14 13.33 14 13.4 14 13.47V13.5\"></path>\n<path stroke-linejoin=\"round\" stroke-linecap=\"round\" stroke-miterlimit=\"10\" stroke-width=\"2\" stroke=\"\" d=\"M9 8.5C7.23 8.97 6.07 10.84 6.01 13.27C6 13.33 6 13.4 6 13.47V13.5\"></path>\n<path stroke-linejoin=\"round\" stroke-linecap=\"round\" stroke-miterlimit=\"10\" stroke-width=\"2\" stroke=\"\" d=\"M15.97 11.5H16.04C17.12 11.5 18 12.38 18 13.47V13.53C18 14.62 17.12 15.5 16.03 15.5H15.96C14.88 15.5 14 14.62 14 13.53V13.46C14 12.38 14.88 11.5 15.97 11.5Z\"></path>\n<path stroke-linejoin=\"round\" stroke-linecap=\"round\" stroke-miterlimit=\"10\" stroke-width=\"2\" stroke=\"\" d=\"M7.97 11.5H8.04C9.12 11.5 10 12.38 10 13.47V13.53C10 14.62 9.12 15.5 8.03 15.5H7.97C6.88 15.5 6 14.62 6 13.53V13.46C6 12.38 6.88 11.5 7.97 11.5Z\"></path>\n</svg>\n</span><p>数据库：Sqlserver</p></blockquote>\n<blockquote><span class=\"custom-blockquote-svg\"><svg width=\"24\" height=\"24\" viewBox=\"0 0 24 24\" fill=\"\" xmlns=\"http://www.w3.org/2000/svg\" data-reactroot=\"\">\n<path fill=\"\" d=\"M22 12C22 6.5 17.5 2 12 2C6.5 2 2 6.5 2 12C2 17.5 6.5 22 12 22C13.8 22 15.5 21.5 17 20.6L22 22L20.7 17C21.5 15.5 22 13.8 22 12Z\" undefined=\"1\"></path>\n<path fill=\"\" d=\"M15.97 11.5H16.04C17.12 11.5 18 12.38 18 13.47V13.53C18 14.62 17.12 15.5 16.03 15.5H15.96C14.88 15.5 14 14.62 14 13.53V13.46C14 12.38 14.88 11.5 15.97 11.5Z\" undefined=\"1\"></path>\n<path fill=\"\" d=\"M7.97 11.5H8.04C9.12 11.5 10 12.38 10 13.47V13.53C10 14.62 9.12 15.5 8.03 15.5H7.97C6.88 15.5 6 14.62 6 13.53V13.46C6 12.38 6.88 11.5 7.97 11.5Z\" undefined=\"1\"></path>\n<path stroke-linejoin=\"round\" stroke-linecap=\"round\" stroke-miterlimit=\"10\" stroke-width=\"2\" stroke=\"\" d=\"M17 8.5C15.23 8.97 14.07 10.84 14.01 13.27C14 13.33 14 13.4 14 13.47V13.5\"></path>\n<path stroke-linejoin=\"round\" stroke-linecap=\"round\" stroke-miterlimit=\"10\" stroke-width=\"2\" stroke=\"\" d=\"M9 8.5C7.23 8.97 6.07 10.84 6.01 13.27C6 13.33 6 13.4 6 13.47V13.5\"></path>\n<path stroke-linejoin=\"round\" stroke-linecap=\"round\" stroke-miterlimit=\"10\" stroke-width=\"2\" stroke=\"\" d=\"M15.97 11.5H16.04C17.12 11.5 18 12.38 18 13.47V13.53C18 14.62 17.12 15.5 16.03 15.5H15.96C14.88 15.5 14 14.62 14 13.53V13.46C14 12.38 14.88 11.5 15.97 11.5Z\"></path>\n<path stroke-linejoin=\"round\" stroke-linecap=\"round\" stroke-miterlimit=\"10\" stroke-width=\"2\" stroke=\"\" d=\"M7.97 11.5H8.04C9.12 11.5 10 12.38 10 13.47V13.53C10 14.62 9.12 15.5 8.03 15.5H7.97C6.88 15.5 6 14.62 6 13.53V13.46C6 12.38 6.88 11.5 7.97 11.5Z\"></path>\n</svg>\n</span><p>后端： Springboot+mybatis+maven</p></blockquote>\n<blockquote><span class=\"custom-blockquote-svg\"><svg width=\"24\" height=\"24\" viewBox=\"0 0 24 24\" fill=\"\" xmlns=\"http://www.w3.org/2000/svg\" data-reactroot=\"\">\n<path fill=\"\" d=\"M22 12C22 6.5 17.5 2 12 2C6.5 2 2 6.5 2 12C2 17.5 6.5 22 12 22C13.8 22 15.5 21.5 17 20.6L22 22L20.7 17C21.5 15.5 22 13.8 22 12Z\" undefined=\"1\"></path>\n<path fill=\"\" d=\"M15.97 11.5H16.04C17.12 11.5 18 12.38 18 13.47V13.53C18 14.62 17.12 15.5 16.03 15.5H15.96C14.88 15.5 14 14.62 14 13.53V13.46C14 12.38 14.88 11.5 15.97 11.5Z\" undefined=\"1\"></path>\n<path fill=\"\" d=\"M7.97 11.5H8.04C9.12 11.5 10 12.38 10 13.47V13.53C10 14.62 9.12 15.5 8.03 15.5H7.97C6.88 15.5 6 14.62 6 13.53V13.46C6 12.38 6.88 11.5 7.97 11.5Z\" undefined=\"1\"></path>\n<path stroke-linejoin=\"round\" stroke-linecap=\"round\" stroke-miterlimit=\"10\" stroke-width=\"2\" stroke=\"\" d=\"M17 8.5C15.23 8.97 14.07 10.84 14.01 13.27C14 13.33 14 13.4 14 13.47V13.5\"></path>\n<path stroke-linejoin=\"round\" stroke-linecap=\"round\" stroke-miterlimit=\"10\" stroke-width=\"2\" stroke=\"\" d=\"M9 8.5C7.23 8.97 6.07 10.84 6.01 13.27C6 13.33 6 13.4 6 13.47V13.5\"></path>\n<path stroke-linejoin=\"round\" stroke-linecap=\"round\" stroke-miterlimit=\"10\" stroke-width=\"2\" stroke=\"\" d=\"M15.97 11.5H16.04C17.12 11.5 18 12.38 18 13.47V13.53C18 14.62 17.12 15.5 16.03 15.5H15.96C14.88 15.5 14 14.62 14 13.53V13.46C14 12.38 14.88 11.5 15.97 11.5Z\"></path>\n<path stroke-linejoin=\"round\" stroke-linecap=\"round\" stroke-miterlimit=\"10\" stroke-width=\"2\" stroke=\"\" d=\"M7.97 11.5H8.04C9.12 11.5 10 12.38 10 13.47V13.53C10 14.62 9.12 15.5 8.03 15.5H7.97C6.88 15.5 6 14.62 6 13.53V13.46C6 12.38 6.88 11.5 7.97 11.5Z\"></path>\n</svg>\n</span><p>前端： jQuery ajax+Echart可视化图表库</p></blockquote>\n<h2 id=\"功能说明：\"><a href=\"#功能说明：\" class=\"headerlink\" title=\"功能说明：\"></a>功能说明：</h2><blockquote><span class=\"custom-blockquote-svg\"><svg width=\"24\" height=\"24\" viewBox=\"0 0 24 24\" fill=\"\" xmlns=\"http://www.w3.org/2000/svg\" data-reactroot=\"\">\n<path fill=\"\" d=\"M22 12C22 6.5 17.5 2 12 2C6.5 2 2 6.5 2 12C2 17.5 6.5 22 12 22C13.8 22 15.5 21.5 17 20.6L22 22L20.7 17C21.5 15.5 22 13.8 22 12Z\" undefined=\"1\"></path>\n<path fill=\"\" d=\"M15.97 11.5H16.04C17.12 11.5 18 12.38 18 13.47V13.53C18 14.62 17.12 15.5 16.03 15.5H15.96C14.88 15.5 14 14.62 14 13.53V13.46C14 12.38 14.88 11.5 15.97 11.5Z\" undefined=\"1\"></path>\n<path fill=\"\" d=\"M7.97 11.5H8.04C9.12 11.5 10 12.38 10 13.47V13.53C10 14.62 9.12 15.5 8.03 15.5H7.97C6.88 15.5 6 14.62 6 13.53V13.46C6 12.38 6.88 11.5 7.97 11.5Z\" undefined=\"1\"></path>\n<path stroke-linejoin=\"round\" stroke-linecap=\"round\" stroke-miterlimit=\"10\" stroke-width=\"2\" stroke=\"\" d=\"M17 8.5C15.23 8.97 14.07 10.84 14.01 13.27C14 13.33 14 13.4 14 13.47V13.5\"></path>\n<path stroke-linejoin=\"round\" stroke-linecap=\"round\" stroke-miterlimit=\"10\" stroke-width=\"2\" stroke=\"\" d=\"M9 8.5C7.23 8.97 6.07 10.84 6.01 13.27C6 13.33 6 13.4 6 13.47V13.5\"></path>\n<path stroke-linejoin=\"round\" stroke-linecap=\"round\" stroke-miterlimit=\"10\" stroke-width=\"2\" stroke=\"\" d=\"M15.97 11.5H16.04C17.12 11.5 18 12.38 18 13.47V13.53C18 14.62 17.12 15.5 16.03 15.5H15.96C14.88 15.5 14 14.62 14 13.53V13.46C14 12.38 14.88 11.5 15.97 11.5Z\"></path>\n<path stroke-linejoin=\"round\" stroke-linecap=\"round\" stroke-miterlimit=\"10\" stroke-width=\"2\" stroke=\"\" d=\"M7.97 11.5H8.04C9.12 11.5 10 12.38 10 13.47V13.53C10 14.62 9.12 15.5 8.03 15.5H7.97C6.88 15.5 6 14.62 6 13.53V13.46C6 12.38 6.88 11.5 7.97 11.5Z\"></path>\n</svg>\n</span><ol>\n<li>接收来自下位机的心率、体温等数据，将其存入Sqlserver数据库中</li>\n</ol></blockquote>\n<blockquote><span class=\"custom-blockquote-svg\"><svg width=\"24\" height=\"24\" viewBox=\"0 0 24 24\" fill=\"\" xmlns=\"http://www.w3.org/2000/svg\" data-reactroot=\"\">\n<path fill=\"\" d=\"M22 12C22 6.5 17.5 2 12 2C6.5 2 2 6.5 2 12C2 17.5 6.5 22 12 22C13.8 22 15.5 21.5 17 20.6L22 22L20.7 17C21.5 15.5 22 13.8 22 12Z\" undefined=\"1\"></path>\n<path fill=\"\" d=\"M15.97 11.5H16.04C17.12 11.5 18 12.38 18 13.47V13.53C18 14.62 17.12 15.5 16.03 15.5H15.96C14.88 15.5 14 14.62 14 13.53V13.46C14 12.38 14.88 11.5 15.97 11.5Z\" undefined=\"1\"></path>\n<path fill=\"\" d=\"M7.97 11.5H8.04C9.12 11.5 10 12.38 10 13.47V13.53C10 14.62 9.12 15.5 8.03 15.5H7.97C6.88 15.5 6 14.62 6 13.53V13.46C6 12.38 6.88 11.5 7.97 11.5Z\" undefined=\"1\"></path>\n<path stroke-linejoin=\"round\" stroke-linecap=\"round\" stroke-miterlimit=\"10\" stroke-width=\"2\" stroke=\"\" d=\"M17 8.5C15.23 8.97 14.07 10.84 14.01 13.27C14 13.33 14 13.4 14 13.47V13.5\"></path>\n<path stroke-linejoin=\"round\" stroke-linecap=\"round\" stroke-miterlimit=\"10\" stroke-width=\"2\" stroke=\"\" d=\"M9 8.5C7.23 8.97 6.07 10.84 6.01 13.27C6 13.33 6 13.4 6 13.47V13.5\"></path>\n<path stroke-linejoin=\"round\" stroke-linecap=\"round\" stroke-miterlimit=\"10\" stroke-width=\"2\" stroke=\"\" d=\"M15.97 11.5H16.04C17.12 11.5 18 12.38 18 13.47V13.53C18 14.62 17.12 15.5 16.03 15.5H15.96C14.88 15.5 14 14.62 14 13.53V13.46C14 12.38 14.88 11.5 15.97 11.5Z\"></path>\n<path stroke-linejoin=\"round\" stroke-linecap=\"round\" stroke-miterlimit=\"10\" stroke-width=\"2\" stroke=\"\" d=\"M7.97 11.5H8.04C9.12 11.5 10 12.38 10 13.47V13.53C10 14.62 9.12 15.5 8.03 15.5H7.97C6.88 15.5 6 14.62 6 13.53V13.46C6 12.38 6.88 11.5 7.97 11.5Z\"></path>\n</svg>\n</span><ol start=\"2\">\n<li>处理来自前端获取数据的请求，将数据以json的形式返回给前端</li>\n</ol></blockquote>\n<h2 id=\"数据库建表语句：\"><a href=\"#数据库建表语句：\" class=\"headerlink\" title=\"数据库建表语句：\"></a>数据库建表语句：</h2><pre class=\"line-numbers language-sql\" data-language=\"sql\"><code class=\"language-sql\">use hello_world\ngo\n\ncreate table endDeviceData\n(\n    id                int identity\n        primary key,\n    temperature       float    default 0 not null,\n    heartbeat_rate    smallint default 0 not null,\n    oxygen_saturation float    default 0 not null\n)\ngo</code></pre>\n\n<h2 id=\"开发流程：\"><a href=\"#开发流程：\" class=\"headerlink\" title=\"开发流程：\"></a>开发流程：</h2><p>利用maven构建springboot项目</p>\n<ul>\n<li><p>项目配置依赖:.&#x2F;pom.xml:</p>\n<pre class=\"line-numbers language-markup\" data-language=\"markup\"><code class=\"language-markup\">&lt;?xml version&#x3D;&quot;1.0&quot; encoding&#x3D;&quot;UTF-8&quot;?&gt;\n&lt;project xmlns&#x3D;&quot;http:&#x2F;&#x2F;maven.apache.org&#x2F;POM&#x2F;4.0.0&quot; xmlns:xsi&#x3D;&quot;http:&#x2F;&#x2F;www.w3.org&#x2F;2001&#x2F;XMLSchema-instance&quot;\n         xsi:schemaLocation&#x3D;&quot;http:&#x2F;&#x2F;maven.apache.org&#x2F;POM&#x2F;4.0.0 https:&#x2F;&#x2F;maven.apache.org&#x2F;xsd&#x2F;maven-4.0.0.xsd&quot;&gt;\n    &lt;modelVersion&gt;4.0.0&lt;&#x2F;modelVersion&gt;\n    &lt;parent&gt;\n        &lt;groupId&gt;org.springframework.boot&lt;&#x2F;groupId&gt;\n        &lt;artifactId&gt;spring-boot-starter-parent&lt;&#x2F;artifactId&gt;\n        &lt;version&gt;2.7.5&lt;&#x2F;version&gt;\n        &lt;relativePath&#x2F;&gt; &lt;!-- lookup parent from repository --&gt;\n    &lt;&#x2F;parent&gt;\n    &lt;groupId&gt;com.example&lt;&#x2F;groupId&gt;\n    &lt;artifactId&gt;SpringBootReview&lt;&#x2F;artifactId&gt;\n    &lt;version&gt;0.0.1-SNAPSHOT&lt;&#x2F;version&gt;\n    &lt;name&gt;SpringBootReview&lt;&#x2F;name&gt;\n    &lt;description&gt;SpringBootReview&lt;&#x2F;description&gt;\n    &lt;properties&gt;\n        &lt;java.version&gt;11&lt;&#x2F;java.version&gt;\n    &lt;&#x2F;properties&gt;\n    &lt;dependencies&gt;\n        &lt;dependency&gt;\n            &lt;groupId&gt;org.mybatis.spring.boot&lt;&#x2F;groupId&gt;\n            &lt;artifactId&gt;mybatis-spring-boot-starter&lt;&#x2F;artifactId&gt;\n            &lt;version&gt;3.0.0&lt;&#x2F;version&gt;\n\n        &lt;&#x2F;dependency&gt;\n        &lt;dependency&gt;\n            &lt;groupId&gt;org.springframework.boot&lt;&#x2F;groupId&gt;\n            &lt;artifactId&gt;spring-boot-starter-thymeleaf&lt;&#x2F;artifactId&gt;\n        &lt;&#x2F;dependency&gt;\n        &lt;dependency&gt;\n            &lt;groupId&gt;org.springframework.boot&lt;&#x2F;groupId&gt;\n            &lt;artifactId&gt;spring-boot-starter-web&lt;&#x2F;artifactId&gt;\n        &lt;&#x2F;dependency&gt;\n        &lt;dependency&gt;\n            &lt;groupId&gt;com.microsoft.sqlserver&lt;&#x2F;groupId&gt;\n            &lt;artifactId&gt;mssql-jdbc&lt;&#x2F;artifactId&gt;\n            &lt;version&gt;11.2.0.jre11&lt;&#x2F;version&gt;\n        &lt;&#x2F;dependency&gt;\n        &lt;dependency&gt;\n            &lt;groupId&gt;org.springframework.boot&lt;&#x2F;groupId&gt;\n            &lt;artifactId&gt;spring-boot-devtools&lt;&#x2F;artifactId&gt;\n            &lt;scope&gt;runtime&lt;&#x2F;scope&gt;\n            &lt;optional&gt;true&lt;&#x2F;optional&gt;\n        &lt;&#x2F;dependency&gt;\n        &lt;dependency&gt;\n            &lt;groupId&gt;org.springframework.boot&lt;&#x2F;groupId&gt;\n            &lt;artifactId&gt;spring-boot-configuration-processor&lt;&#x2F;artifactId&gt;\n            &lt;optional&gt;true&lt;&#x2F;optional&gt;\n        &lt;&#x2F;dependency&gt;\n        &lt;dependency&gt;\n            &lt;groupId&gt;com.alibaba&lt;&#x2F;groupId&gt;\n            &lt;artifactId&gt;druid-spring-boot-starter&lt;&#x2F;artifactId&gt;\n            &lt;version&gt;1.2.15&lt;&#x2F;version&gt;\n        &lt;&#x2F;dependency&gt;\n        &lt;dependency&gt;\n            &lt;groupId&gt;org.projectlombok&lt;&#x2F;groupId&gt;\n            &lt;artifactId&gt;lombok&lt;&#x2F;artifactId&gt;\n            &lt;optional&gt;true&lt;&#x2F;optional&gt;\n        &lt;&#x2F;dependency&gt;\n        &lt;dependency&gt;\n            &lt;groupId&gt;org.springframework.boot&lt;&#x2F;groupId&gt;\n            &lt;artifactId&gt;spring-boot-starter-test&lt;&#x2F;artifactId&gt;\n            &lt;scope&gt;test&lt;&#x2F;scope&gt;\n        &lt;&#x2F;dependency&gt;\n        &lt;dependency&gt;\n            &lt;groupId&gt;org.jetbrains&lt;&#x2F;groupId&gt;\n            &lt;artifactId&gt;annotations&lt;&#x2F;artifactId&gt;\n            &lt;version&gt;RELEASE&lt;&#x2F;version&gt;\n            &lt;scope&gt;compile&lt;&#x2F;scope&gt;\n        &lt;&#x2F;dependency&gt;\n    &lt;&#x2F;dependencies&gt;\n\n    &lt;build&gt;\n        &lt;plugins&gt;\n            &lt;plugin&gt;\n                &lt;groupId&gt;org.springframework.boot&lt;&#x2F;groupId&gt;\n                &lt;artifactId&gt;spring-boot-maven-plugin&lt;&#x2F;artifactId&gt;\n                &lt;configuration&gt;\n                    &lt;excludes&gt;\n                        &lt;exclude&gt;\n                            &lt;groupId&gt;org.projectlombok&lt;&#x2F;groupId&gt;\n                            &lt;artifactId&gt;lombok&lt;&#x2F;artifactId&gt;\n                        &lt;&#x2F;exclude&gt;\n                    &lt;&#x2F;excludes&gt;\n                &lt;&#x2F;configuration&gt;\n            &lt;&#x2F;plugin&gt;\n        &lt;&#x2F;plugins&gt;\n    &lt;&#x2F;build&gt;\n\n&lt;&#x2F;project&gt;</code></pre>\n</li>\n<li><p>项目具体配置：application.yml</p>\n<pre class=\"line-numbers language-properties\" data-language=\"properties\"><code class=\"language-properties\">spring.datasource.url&#x3D;jdbc:sqlserver:&#x2F;&#x2F;localhost:1433;trustServerCertificate&#x3D;true\nspring.datasource.driverClassName&#x3D;com.microsoft.sqlserver.jdbc.SQLServerDriver\nspring.datasource.username&#x3D;sa\nspring.datasource.password&#x3D;123456\n\nspring.datasource.druid.connect-timeout&#x3D; 3000\nmybatis.config-location&#x3D; classpath:mybatis&#x2F;mybatis-config.xml\nmybatis.mapper-locations&#x3D; classpath:mybatis&#x2F;mapper&#x2F;DataMapper.xml</code></pre></li>\n</ul>\n<h2 id=\"编写Mapper接口\"><a href=\"#编写Mapper接口\" class=\"headerlink\" title=\"编写Mapper接口\"></a>编写Mapper接口</h2><p>DataMapper.java:</p>\n<pre class=\"line-numbers language-java\" data-language=\"java\"><code class=\"language-java\">@Mapper\npublic interface DataMapper &#123;\n public DeviceData selectData();\n public int insertData(@Param(&quot;temp&quot;) Float temp, @Param(&quot;heartbeat&quot;)Integer heartbeat, @Param(&quot;os&quot;)Float os);\n&#125;</code></pre>\n\n<p>DataMapper.xml</p>\n<pre class=\"line-numbers language-markup\" data-language=\"markup\"><code class=\"language-markup\">&lt;?xml version&#x3D;&quot;1.0&quot; encoding&#x3D;&quot;UTF-8&quot; ?&gt;\n&lt;!DOCTYPE mapper\n        PUBLIC &quot;-&#x2F;&#x2F;mybatis.org&#x2F;&#x2F;DTD Mapper 3.0&#x2F;&#x2F;EN&quot;\n        &quot;http:&#x2F;&#x2F;mybatis.org&#x2F;dtd&#x2F;mybatis-3-mapper.dtd&quot;&gt;\n&lt;mapper namespace&#x3D;&quot;com.example.springbootreview.mapper.DataMapper&quot;&gt;\n    &lt;insert id&#x3D;&quot;insertData&quot; &gt;\n        insert into  hello_world.dbo.endDeviceData\n            (temperature, heartbeat_rate, oxygen_saturation)values\n            (#&#123;temp&#125;,#&#123;heartbeat&#125;,#&#123;os&#125;);\n    &lt;&#x2F;insert&gt;\n    &lt;select id&#x3D;&quot;selectData&quot; resultType&#x3D;&quot;com.example.springbootreview.pojo.DeviceData&quot;&gt;\n        select TOP 1 * from hello_world.dbo.endDeviceData order by id desc ;\n    &lt;&#x2F;select&gt;\n&lt;&#x2F;mapper&gt;</code></pre>\n\n<h2 id=\"编写Controller接口：\"><a href=\"#编写Controller接口：\" class=\"headerlink\" title=\"编写Controller接口：\"></a>编写Controller接口：</h2><pre class=\"line-numbers language-java\" data-language=\"java\"><code class=\"language-java\">@Controller\npublic class myController &#123;\n\n    @Autowired\n    DeviceData data;\n    @Autowired\n    DataServiceImpl dataService;\n\n\n    @GetMapping(&quot;&#x2F;&quot;)\n    public String home()&#123;\n\n        return &quot;test1&quot;;\n\n    &#125;\n    &#x2F;&#x2F;硬件端上传数据\n    @PostMapping(&quot;&#x2F;updateData&quot;)\n    public String updateDataFromDevice(@RequestBody DeviceData data)&#123;\n        System.out.println(&quot;ID &#x3D; &quot; + data.getId());\n        System.out.println(&quot;Temperature &#x3D; &quot; + data.getTemperature());\n        System.out.println(&quot;HeartBeatRate &#x3D; &quot; + data.getHeartBeatRate());\n        System.out.println(&quot;OSRate &#x3D; &quot; + data.getOxygenSaturation());\n        log.info(data.toString());\n        dataService.updateData(data);\n\n\n        return &quot;test1&quot;;\n    &#125;\n    &#x2F;&#x2F;处理前端数据请求\n    @GetMapping(&quot;&#x2F;requestData&quot;)\n    @ResponseBody\n    public DeviceData requestData()&#123;\n        DeviceData deviceData &#x3D; dataService.selectDeviceData();\n        log.info(deviceData.toString());\n\n        return deviceData;\n\n\n    &#125;\n&#125;</code></pre>\n\n<h2 id=\"编写前端WEB页面\"><a href=\"#编写前端WEB页面\" class=\"headerlink\" title=\"编写前端WEB页面\"></a>编写前端WEB页面</h2><p>通过setInterval函数定时发送ajax请求，获取服务器中的数据：</p>\n<pre class=\"line-numbers language-javascript\" data-language=\"javascript\"><code class=\"language-javascript\">setInterval(\n        function ()&#123;\n            $.ajax(&#123;\n                type : &quot;get&quot;,\n                url: &quot;requestData&quot;,\n                dataType: &#39;json&#39;,\n                success: function (data)&#123;\n\n                    console.log(data);\n                    let t  &#x3D; JSON.stringify(data)\n                    &#x2F;&#x2F;console.log(obj)\n\n                    var obj  &#x3D; JSON.parse(t)\n\n                    console.log(obj.id)\n                    console.log(obj.temperature)\n                    console.log(obj.oxygenSaturation)\n                    console.log(obj.heartBeatRate)\n\n                    myChart.setOption(&#123;\n                        series: [\n                            &#123;\n                                name: &#39;Fake Data1&#39;,\n                                data: data1\n                            &#125;,\n                            &#123;\n                                name: &#39;Fake Data2&#39;,\n                                data: data2\n                            &#125;,\n                            &#123;\n                                name: &#39;Fake Data3&#39;,\n                                data: data3\n                            &#125;\n                        ]\n                    &#125;);\n\n                &#125;\n            &#125;);\n\n        &#125;,1000\n\n    )</code></pre>\n\n<p>实现效果：</p>\n<p><img src=\"/img/web.png\"></p>\n","feature":true,"text":"环境说明： 开发软件环境：IDEA 2022.2.3+Postman+MicroSoft Sqlserver Manager 2015 数据库：Sqlserver 后端： Springboot+mybatis+maven 前端： jQuery ajax+Echart可视化图表库 ...","link":"","photos":[],"count_time":{"symbolsCount":"9.4k","symbolsTime":"9 mins."},"categories":[{"name":"课设","slug":"课设","count":1,"path":"api/categories/课设.json"}],"tags":[],"toc":"<ol class=\"toc\"><li class=\"toc-item toc-level-2\"><a class=\"toc-link\" href=\"#%E7%8E%AF%E5%A2%83%E8%AF%B4%E6%98%8E%EF%BC%9A\"><span class=\"toc-text\">环境说明：</span></a></li><li class=\"toc-item toc-level-2\"><a class=\"toc-link\" href=\"#%E5%8A%9F%E8%83%BD%E8%AF%B4%E6%98%8E%EF%BC%9A\"><span class=\"toc-text\">功能说明：</span></a></li><li class=\"toc-item toc-level-2\"><a class=\"toc-link\" href=\"#%E6%95%B0%E6%8D%AE%E5%BA%93%E5%BB%BA%E8%A1%A8%E8%AF%AD%E5%8F%A5%EF%BC%9A\"><span class=\"toc-text\">数据库建表语句：</span></a></li><li class=\"toc-item toc-level-2\"><a class=\"toc-link\" href=\"#%E5%BC%80%E5%8F%91%E6%B5%81%E7%A8%8B%EF%BC%9A\"><span class=\"toc-text\">开发流程：</span></a></li><li class=\"toc-item toc-level-2\"><a class=\"toc-link\" href=\"#%E7%BC%96%E5%86%99Mapper%E6%8E%A5%E5%8F%A3\"><span class=\"toc-text\">编写Mapper接口</span></a></li><li class=\"toc-item toc-level-2\"><a class=\"toc-link\" href=\"#%E7%BC%96%E5%86%99Controller%E6%8E%A5%E5%8F%A3%EF%BC%9A\"><span class=\"toc-text\">编写Controller接口：</span></a></li><li class=\"toc-item toc-level-2\"><a class=\"toc-link\" href=\"#%E7%BC%96%E5%86%99%E5%89%8D%E7%AB%AFWEB%E9%A1%B5%E9%9D%A2\"><span class=\"toc-text\">编写前端WEB页面</span></a></li></ol>","author":{"name":"Agoni","slug":"blog-author","avatar":"https://img-blog.csdnimg.cn/20210313122054101.png","link":"/","description":"","socials":{"github":"","twitter":"","stackoverflow":"","wechat":"","qq":"","weibo":"","zhihu":"","csdn":"","juejin":"","customs":{}}},"mapped":true,"prev_post":{"title":"hello","uid":"46426c79fe8370cebf57bb63c792f570","slug":"hello","date":"2022-12-21T13:59:51.521Z","updated":"2022-12-21T13:59:51.522Z","comments":true,"path":"api/articles/hello.json","keywords":null,"cover":null,"text":"不知不觉已经接近大三上学期的尾声了，不得不感慨时光过的好快啊！ 今年的蓝桥杯变数很大，首先，本来已经被我稳稳拿捏的物联网赛道突然更换了开发板，但是学校的实验室资金不足，所以没有办法给我们购买开发板学习，如果自己买的话一个板子就要花400多大洋。再加上蓝桥杯本来就有300块报名费，...","link":"","photos":[],"count_time":{"symbolsCount":477,"symbolsTime":"1 mins."},"categories":[],"tags":[],"author":{"name":"Agoni","slug":"blog-author","avatar":"https://img-blog.csdnimg.cn/20210313122054101.png","link":"/","description":"","socials":{"github":"","twitter":"","stackoverflow":"","wechat":"","qq":"","weibo":"","zhihu":"","csdn":"","juejin":"","customs":{}}},"feature":true},"next_post":{}}